context_generator/__init__.py
context_generator/cli.py
context_generator/core.py
tests/__init__.py
tests/test_cli.py
tests/test_core.py
context_generator-0.1.1.dist-info/LICENCE
context_generator-0.1.1.dist-info/METADATA
context_generator-0.1.1.dist-info/WHEEL
context_generator-0.1.1.dist-info/entry_points.txt
context_generator-0.1.1.dist-info/top_level.txt
context_generator-0.1.1.dist-info/RECORD
