Metadata-Version: 2.2
Name: context-generator
Version: 0.1.1
Summary: Generate file tree and file contents for coding assistance with LLMs.
Home-page: https://github.com/aldo-g/context-gen
Author: Alastair Grant
Author-email: aldo.e.george@gmail.com
Project-URL: Bug Reports, https://github.com/aldo-g/context-gen/issues
Project-URL: Source, https://github.com/aldo-g/context-gen
Keywords: context generation file tree LLMs coding assistance
Classifier: Programming Language :: Python :: 3
Classifier: Programming Language :: Python :: 3.9
Classifier: Programming Language :: Python :: 3.10
Classifier: Programming Language :: Python :: 3.11
Classifier: License :: OSI Approved :: MIT License
Classifier: Operating System :: OS Independent
Classifier: Intended Audience :: Developers
Classifier: Topic :: Software Development :: Build Tools
Requires-Python: >=3.9
License-File: LICENCE
Provides-Extra: dev
Requires-Dist: pytest>=6.0.0; extra == "dev"
Requires-Dist: flake8>=3.9.2; extra == "dev"
Requires-Dist: black>=23.3.0; extra == "dev"
Dynamic: author
Dynamic: author-email
Dynamic: classifier
Dynamic: description
Dynamic: description-content-type
Dynamic: home-page
Dynamic: keywords
Dynamic: project-url
Dynamic: provides-extra
Dynamic: requires-python
Dynamic: summary
